<?xml version="1.0" ?>
<UAVLogs>
  <LogEntry>
    <Timestamp>1736780331.5521162</Timestamp>
    <Position>
      <X>0.0</X>
      <Y>0.0</Y>
      <Z>0.21852347254753113</Z>
    </Position>
    <Velocity>
      <VX>0.0</VX>
      <VY>0.0</VY>
      <VZ>0.07962743937969208</VZ>
    </Velocity>
    <EulerAngles>
      <Pitch>0.0</Pitch>
      <Roll>0.0</Roll>
      <Yaw>2.044518183593083</Yaw>
    </EulerAngles>
    <AngularVelocity>
      <RollRate>0.0</RollRate>
      <PitchRate>0.0</PitchRate>
      <YawRate>0.1410079300403595</YawRate>
    </AngularVelocity>
  </LogEntry>
</UAVLogs>
