<?xml version="1.0" ?>
<UAVLogs>
  <LogEntry>
    <Timestamp>1736936495.363528</Timestamp>
    <Position>
      <X>0.0</X>
      <Y>0.0</Y>
      <Z>-0.9223700165748596</Z>
    </Position>
    <Velocity>
      <VX>0.0</VX>
      <VY>0.0</VY>
      <VZ>-0.0018339100060984492</VZ>
    </Velocity>
    <EulerAngles>
      <Pitch>0.0</Pitch>
      <Roll>0.0</Roll>
      <Yaw>0.0</Yaw>
    </EulerAngles>
    <AngularVelocity>
      <RollRate>0.0</RollRate>
      <PitchRate>0.0</PitchRate>
      <YawRate>0.0</YawRate>
    </AngularVelocity>
  </LogEntry>
  <LogEntry>
    <Timestamp>1736936495.9076905</Timestamp>
    <Position>
      <X>0.0</X>
      <Y>0.0</Y>
      <Z>-0.9239976406097412</Z>
    </Position>
    <Velocity>
      <VX>0.0</VX>
      <VY>0.0</VY>
      <VZ>-0.0006724168779328465</VZ>
    </Velocity>
    <EulerAngles>
      <Pitch>0.0</Pitch>
      <Roll>0.0</Roll>
      <Yaw>0.0</Yaw>
    </EulerAngles>
    <AngularVelocity>
      <RollRate>0.0</RollRate>
      <PitchRate>0.0</PitchRate>
      <YawRate>0.0</YawRate>
    </AngularVelocity>
  </LogEntry>
  <LogEntry>
    <Timestamp>1736936496.7182188</Timestamp>
    <Position>
      <X>0.0</X>
      <Y>0.0</Y>
      <Z>-0.9243727922439575</Z>
    </Position>
    <Velocity>
      <VX>0.0</VX>
      <VY>0.0</VY>
      <VZ>-0.000403143058065325</VZ>
    </Velocity>
    <EulerAngles>
      <Pitch>0.0</Pitch>
      <Roll>0.0</Roll>
      <Yaw>0.0</Yaw>
    </EulerAngles>
    <AngularVelocity>
      <RollRate>0.0</RollRate>
      <PitchRate>0.0</PitchRate>
      <YawRate>0.0</YawRate>
    </AngularVelocity>
  </LogEntry>
  <LogEntry>
    <Timestamp>1736936497.5489082</Timestamp>
    <Position>
      <X>0.04528205469250679</X>
      <Y>-5.524172785875692e-10</Y>
      <Z>-0.9255168437957764</Z>
    </Position>
    <Velocity>
      <VX>0.2704309821128845</VX>
      <VY>-5.865754548750601e-09</VY>
      <VZ>0.04302380234003067</VZ>
    </Velocity>
    <EulerAngles>
      <Pitch>0.033060178868991805</Pitch>
      <Roll>4.315883253971026e-11</Roll>
      <Yaw>-2.6396454715373242e-09</Yaw>
    </EulerAngles>
    <AngularVelocity>
      <RollRate>5.769738020688919e-09</RollRate>
      <PitchRate>0.005460401531308889</PitchRate>
      <YawRate>-6.84289558350315e-09</YawRate>
    </AngularVelocity>
  </LogEntry>
  <LogEntry>
    <Timestamp>1736936498.3561149</Timestamp>
    <Position>
      <X>0.24203220009803772</X>
      <Y>-3.8811434066587935e-09</Y>
      <Z>-0.8871251344680786</Z>
    </Position>
    <Velocity>
      <VX>0.29483070969581604</VX>
      <VY>-7.552093173046615e-09</VY>
      <VZ>0.025997504591941833</VZ>
    </Velocity>
    <EulerAngles>
      <Pitch>0.0414666921138382</Pitch>
      <Roll>-3.4078827248882968e-09</Roll>
      <Yaw>-7.199220216510069e-09</Yaw>
    </EulerAngles>
    <AngularVelocity>
      <RollRate>-9.937695999440166e-09</RollRate>
      <PitchRate>0.0007113193278200924</PitchRate>
      <YawRate>-1.5883938608851622e-09</YawRate>
    </AngularVelocity>
  </LogEntry>
  <LogEntry>
    <Timestamp>1736936499.169731</Timestamp>
    <Position>
      <X>0.4597187638282776</X>
      <Y>-1.6376564104803037e-08</Y>
      <Z>-0.85448157787323</Z>
    </Position>
    <Velocity>
      <VX>0.28252729773521423</VX>
      <VY>-2.8534740792451885e-08</VY>
      <VZ>0.022279029712080956</VZ>
    </Velocity>
    <EulerAngles>
      <Pitch>0.043027621831483204</Pitch>
      <Roll>7.646202970915995e-09</Roll>
      <Yaw>-7.738734531094924e-09</Yaw>
    </EulerAngles>
    <AngularVelocity>
      <RollRate>-4.2413557110876354e-09</RollRate>
      <PitchRate>-0.0011637818533927202</PitchRate>
      <YawRate>6.658990692187672e-09</YawRate>
    </AngularVelocity>
  </LogEntry>
  <LogEntry>
    <Timestamp>1736936499.9827557</Timestamp>
    <Position>
      <X>0.6715340614318848</X>
      <Y>-2.5901380595882983e-08</Y>
      <Z>-0.823553740978241</Z>
    </Position>
    <Velocity>
      <VX>0.2848121225833893</VX>
      <VY>6.633085636309488e-09</VY>
      <VZ>0.024780940264463425</VZ>
    </Velocity>
    <EulerAngles>
      <Pitch>0.041188673487953444</Pitch>
      <Roll>-7.783167746380032e-09</Roll>
      <Yaw>3.2098762128743134e-10</Yaw>
    </EulerAngles>
    <AngularVelocity>
      <RollRate>-2.8177746358437616e-08</RollRate>
      <PitchRate>-0.0007706448086537421</PitchRate>
      <YawRate>1.6984063933023208e-08</YawRate>
    </AngularVelocity>
  </LogEntry>
  <LogEntry>
    <Timestamp>1736936500.7922807</Timestamp>
    <Position>
      <X>0.8817597031593323</X>
      <Y>-3.6184797380656164e-08</Y>
      <Z>-0.7925006151199341</Z>
    </Position>
    <Velocity>
      <VX>0.28880348801612854</VX>
      <VY>-6.927482587570921e-08</VY>
      <VZ>0.02648000791668892</VZ>
    </Velocity>
    <EulerAngles>
      <Pitch>0.04057124060017901</Pitch>
      <Roll>3.484823236172992e-09</Roll>
      <Yaw>1.2546330629440704e-08</Yaw>
    </EulerAngles>
    <AngularVelocity>
      <RollRate>4.9741061047825497e-08</RollRate>
      <PitchRate>-8.545495802536607e-05</PitchRate>
      <YawRate>1.0666671990122722e-08</YawRate>
    </AngularVelocity>
  </LogEntry>
  <LogEntry>
    <Timestamp>1736936501.3304868</Timestamp>
    <Position>
      <X>1.092158317565918</X>
      <Y>-7.692311498885829e-08</Y>
      <Z>-0.7613168358802795</Z>
    </Position>
    <Velocity>
      <VX>0.288631409406662</VX>
      <VY>-3.088458200295463e-08</VY>
      <VZ>0.025813402608036995</VZ>
    </Velocity>
    <EulerAngles>
      <Pitch>0.04079579747523314</Pitch>
      <Roll>-1.506839334914285e-08</Roll>
      <Yaw>1.6387314467387176e-08</Yaw>
    </EulerAngles>
    <AngularVelocity>
      <RollRate>-6.541021235761946e-08</RollRate>
      <PitchRate>0.10424801707267761</PitchRate>
      <YawRate>1.3551181288207204e-09</YawRate>
    </AngularVelocity>
  </LogEntry>
  <LogEntry>
    <Timestamp>1736936502.1459844</Timestamp>
    <Position>
      <X>1.2832634449005127</X>
      <Y>-9.526970501383403e-08</Y>
      <Z>-0.7301919460296631</Z>
    </Position>
    <Velocity>
      <VX>0.3825817108154297</VX>
      <VY>-4.2035985359234473e-08</VY>
      <VZ>0.013985288329422474</VZ>
    </Velocity>
    <EulerAngles>
      <Pitch>0.060743421732032996</Pitch>
      <Roll>1.6244498457091486e-08</Roll>
      <Yaw>1.818816748237275e-08</Yaw>
    </EulerAngles>
    <AngularVelocity>
      <RollRate>-8.814195595618912e-09</RollRate>
      <PitchRate>-0.008311293087899685</PitchRate>
      <YawRate>-1.1145803391343634e-08</YawRate>
    </AngularVelocity>
  </LogEntry>
  <LogEntry>
    <Timestamp>1736936502.957817</Timestamp>
    <Position>
      <X>1.5480905771255493</X>
      <Y>-1.1119719545149565e-07</Y>
      <Z>-0.6994080543518066</Z>
    </Position>
    <Velocity>
      <VX>0.27990636229515076</VX>
      <VY>1.686025541403069e-08</VY>
      <VZ>0.019835563376545906</VZ>
    </Velocity>
    <EulerAngles>
      <Pitch>0.04267269583342554</Pitch>
      <Roll>-4.378738493907628e-09</Roll>
      <Yaw>1.0304711376929838e-08</Yaw>
    </EulerAngles>
    <AngularVelocity>
      <RollRate>-2.2844496072593756e-08</RollRate>
      <PitchRate>-0.0031140658538788557</PitchRate>
      <YawRate>-4.121581742566605e-09</YawRate>
    </AngularVelocity>
  </LogEntry>
  <LogEntry>
    <Timestamp>1736936503.774649</Timestamp>
    <Position>
      <X>1.758674144744873</X>
      <Y>-1.0942044781359073e-07</Y>
      <Z>-0.6703463196754456</Z>
    </Position>
    <Velocity>
      <VX>0.2763257324695587</VX>
      <VY>-7.717307681787133e-08</VY>
      <VZ>0.022907279431819916</VZ>
    </Velocity>
    <EulerAngles>
      <Pitch>0.042293482323877155</Pitch>
      <Roll>-1.5487819506367775e-08</Roll>
      <Yaw>7.08841845453875e-09</Yaw>
    </EulerAngles>
    <AngularVelocity>
      <RollRate>2.0666738009822438e-07</RollRate>
      <PitchRate>-0.00102173478808254</PitchRate>
      <YawRate>-1.1909395247755583e-08</YawRate>
    </AngularVelocity>
  </LogEntry>
</UAVLogs>
